ctp_factors_biaowang
